jinja2_from_json_extension/__init__.py
jinja2_from_json_extension-1.0.1.dist-info/licenses/LICENSE
jinja2_from_json_extension-1.0.1.dist-info/METADATA
jinja2_from_json_extension-1.0.1.dist-info/WHEEL
jinja2_from_json_extension-1.0.1.dist-info/top_level.txt
jinja2_from_json_extension-1.0.1.dist-info/RECORD
