Metadata-Version: 2.4
Name: jinja2_from_json_extension
Version: 1.0.1
Home-page: https://github.com/metwork-framework/jinja2_from_json_extension
License: BSD
License-File: LICENSE
Requires-Dist: jinja2
Dynamic: home-page
Dynamic: license
Dynamic: license-file
Dynamic: requires-dist
